{
    "description": "UEFI firmware for ARM64 virtual machines",
    "interface-types": [
        "uefi"
    ],
    "mapping": {
        "device": "flash",
        "mode" : "split",
        "executable": {
            "filename": "/usr/share/edk2/aarch64/QEMU_EFI-silent-pflash.qcow2",
            "format": "qcow2"
        },
        "nvram-template": {
            "filename": "/usr/share/edk2/aarch64/vars-template-pflash.qcow2",
            "format": "qcow2"
        }
    },
    "targets": [
        {
            "architecture": "aarch64",
            "machines": [
                "virt-*"
            ]
        }
    ],
    "features": [

    ],
    "tags": [

    ]
}
