<image>
	<repository type="rpm-md" alias="fedora" sourcetype="metalink">
		<source path="https://mirrors.fedoraproject.org/metalink?repo=fedora-$releasever&amp;arch=$basearch">
			<signing key="file:///usr/share/distribution-gpg-keys/fedora/RPM-GPG-KEY-fedora-$releasever-primary"/>
		</source>
	</repository>
	<repository type="rpm-md" alias="updates" sourcetype="metalink">
		<source path="https://mirrors.fedoraproject.org/metalink?repo=updates-released-f$releasever&amp;arch=$basearch">
			<signing key="file:///usr/share/distribution-gpg-keys/fedora/RPM-GPG-KEY-fedora-$releasever-primary"/>
		</source>
	</repository>
	<!-- For folks to enable for building images with content in test update repositories -->
	<!--
	<repository type="rpm-md" alias="updates-testing" sourcetype="metalink">
		<source path="https://mirrors.fedoraproject.org/metalink?repo=updates-testing-f$releasever&amp;arch=$basearch">
			<signing key="file:///usr/share/distribution-gpg-keys/fedora/RPM-GPG-KEY-fedora-$releasever-primary"/>
		</source>
	</repository>
	-->
</image>
